mongodb_ai_playground/__init__.py
mongodb_ai_playground/index.css
mongodb_ai_playground/index.js
mongodb_ai_playground/rag_widget.py
mongodb_ai_playground-0.0.9.dist-info/LICENSE
mongodb_ai_playground-0.0.9.dist-info/METADATA
mongodb_ai_playground-0.0.9.dist-info/WHEEL
mongodb_ai_playground-0.0.9.dist-info/top_level.txt
mongodb_ai_playground-0.0.9.dist-info/RECORD
