Metadata-Version: 2.1
Name: mongodb-ai-playground
Version: 0.0.9
Summary: A playground for building RAG applications with MongoDB and Langchain
Home-page: https://github.com/tgourdel/mongodb-rag-playground
Author: Thibaut Gourdel
Author-email: thibaut.gourdel@mongodb.com
License: UNKNOWN
Platform: UNKNOWN
Classifier: Programming Language :: Python :: 3
Classifier: License :: OSI Approved :: MIT License
Classifier: Operating System :: OS Independent
Requires-Python: >=3.7
License-File: LICENSE
Requires-Dist: anywidget
Requires-Dist: traitlets
Requires-Dist: langchain
Requires-Dist: langchain-mongodb
Requires-Dist: langchain-core
